telegram_bot_personnel_data_collector/__init__.py
telegram_bot_personnel_data_collector/__main__.py
telegram_bot_personnel_data_collector/arg_parse.py
telegram_bot_personnel_data_collector/configurations.py
telegram_bot_personnel_data_collector/google_sheets.py
telegram_bot_personnel_data_collector/localisation.py
telegram_bot_personnel_data_collector/session_cache.py
telegram_bot_personnel_data_collector/utils.py
telegram_bot_personnel_data_collector/model/__init__.py
telegram_bot_personnel_data_collector/model/db_model.py
telegram_bot_personnel_data_collector/telegram_api/__init__.py
telegram_bot_personnel_data_collector/telegram_api/handlers.py
telegram_bot_personnel_data_collector/telegram_api/helpers.py
telegram_bot_personnel_data_collector/telegram_api/service.py
telegram_bot_personnel_data_collector-2.6.dist-info/METADATA
telegram_bot_personnel_data_collector-2.6.dist-info/WHEEL
telegram_bot_personnel_data_collector-2.6.dist-info/top_level.txt
telegram_bot_personnel_data_collector-2.6.dist-info/RECORD
