Metadata-Version: 2.1
Name: telegram-bot-personnel-data-collector
Version: 2.6
Summary: UNKNOWN
Home-page: https://github.com/doguz2509/VolunteerHelpGroupBot
Author: Dmitry Oguz
Author-email: doguz2509@gmail.com
License: MIT
Platform: UNKNOWN
Classifier: Programming Language :: Python :: 3
Classifier: Framework :: Robot Framework
Classifier: Framework :: Robot Framework :: Library
Classifier: Operating System :: OS Independent
Classifier: Development Status :: 3 - Alpha
Requires-Dist: PyYAML (~=6.0)
Requires-Dist: aiogram (~=2.20)
Requires-Dist: google-sheets-lib
Requires-Dist: setuptools (~=62.1.0)
Requires-Dist: syncer (~=1.3.0)
